biotree_tools/MMlib3.py
biotree_tools/__init__.py
biotree_tools/_version.py
biotree_tools/alignment_tools.py
biotree_tools/phylo_context.py
biotree_tools/show_tree.py
biotree_tools/tree_classes.py
biotree_tools/tree_tools.py
biotree_tools-0.0.6.dist-info/LICENSE
biotree_tools-0.0.6.dist-info/METADATA
biotree_tools-0.0.6.dist-info/WHEEL
biotree_tools-0.0.6.dist-info/top_level.txt
biotree_tools-0.0.6.dist-info/RECORD
