Metadata-Version: 2.1
Name: biotree-tools
Version: 0.0.6
Summary: Collection of bioinformatics tools related to alignments and phylogenetic trees
Home-page: https://github.com/pypa/biotree_tools
Author: Marco Mariotti
Author-email: marco.mariotti@ub.edu
Classifier: Programming Language :: Python :: 3
Classifier: License :: OSI Approved :: MIT License
Classifier: Operating System :: OS Independent
Requires-Python: >=3.6
License-File: LICENSE
Requires-Dist: biopython
Requires-Dist: easyterm (>=1.0.0)
Requires-Dist: ncbi-db (>=0.1.1)
